morphui-0.3.1.dist-info/METADATA
morphui-0.3.1.dist-info/WHEEL
morphui-0.3.1.dist-info/entry_points.txt
morphui-0.3.1.dist-info/licenses/LICENSE
morphui/__init__.py
morphui/_typing.py
morphui/_version.py
morphui/app.py
morphui/constants.py
morphui/fonts/dmsans/DMSans-Black.ttf
morphui/fonts/dmsans/DMSans-BlackItalic.ttf
morphui/fonts/dmsans/DMSans-Bold.ttf
morphui/fonts/dmsans/DMSans-BoldItalic.ttf
morphui/fonts/dmsans/DMSans-ExtraBold.ttf
morphui/fonts/dmsans/DMSans-ExtraBoldItalic.ttf
morphui/fonts/dmsans/DMSans-ExtraLight.ttf
morphui/fonts/dmsans/DMSans-ExtraLightItalic.ttf
morphui/fonts/dmsans/DMSans-Italic.ttf
morphui/fonts/dmsans/DMSans-Light.ttf
morphui/fonts/dmsans/DMSans-LightItalic.ttf
morphui/fonts/dmsans/DMSans-Medium.ttf
morphui/fonts/dmsans/DMSans-MediumItalic.ttf
morphui/fonts/dmsans/DMSans-Regular.ttf
morphui/fonts/dmsans/DMSans-SemiBold.ttf
morphui/fonts/dmsans/DMSans-SemiBoldItalic.ttf
morphui/fonts/dmsans/DMSans-Thin.ttf
morphui/fonts/dmsans/DMSans-ThinItalic.ttf
morphui/fonts/dmsans/LICENSE.txt
morphui/fonts/inter/Inter-Black.ttf
morphui/fonts/inter/Inter-BlackItalic.ttf
morphui/fonts/inter/Inter-Bold.ttf
morphui/fonts/inter/Inter-BoldItalic.ttf
morphui/fonts/inter/Inter-ExtraBold.ttf
morphui/fonts/inter/Inter-ExtraBoldItalic.ttf
morphui/fonts/inter/Inter-ExtraLight.ttf
morphui/fonts/inter/Inter-ExtraLightItalic.ttf
morphui/fonts/inter/Inter-Italic.ttf
morphui/fonts/inter/Inter-Light.ttf
morphui/fonts/inter/Inter-LightItalic.ttf
morphui/fonts/inter/Inter-Medium.ttf
morphui/fonts/inter/Inter-MediumItalic.ttf
morphui/fonts/inter/Inter-Regular.ttf
morphui/fonts/inter/Inter-SemiBold.ttf
morphui/fonts/inter/Inter-SemiBoldItalic.ttf
morphui/fonts/inter/Inter-Thin.ttf
morphui/fonts/inter/Inter-ThinItalic.ttf
morphui/fonts/inter/InterDisplay-Black.ttf
morphui/fonts/inter/InterDisplay-BlackItalic.ttf
morphui/fonts/inter/InterDisplay-Bold.ttf
morphui/fonts/inter/InterDisplay-BoldItalic.ttf
morphui/fonts/inter/InterDisplay-ExtraBold.ttf
morphui/fonts/inter/InterDisplay-ExtraBoldItalic.ttf
morphui/fonts/inter/InterDisplay-ExtraLight.ttf
morphui/fonts/inter/InterDisplay-ExtraLightItalic.ttf
morphui-0.3.1.dist-info/RECORD
