Metadata-Version: 2.1
Name: MorphUI
Version: 0.3.1
Summary: MorphUI is a creative and flexible UI extension for Kivy, designed to provide developers with a modern and customizable set of components for building beautiful user interfaces. Unlike KivyMD, MorphUI is not bound to Material Design principles, allowing for greater freedom in design and styling.
Author-Email: j4ggr <reto@jaeggli.email>
License: MIT
Requires-Python: >=3.13
Requires-Dist: kivy>=2.3.1
Requires-Dist: material-color-utilities>=0.2.6
